mailer/__init__.py
mailer/aio.py
mailer/blocking.py
mailer/shared.py
wafflehacks_mailer-0.2.2.dist-info/METADATA
wafflehacks_mailer-0.2.2.dist-info/WHEEL
wafflehacks_mailer-0.2.2.dist-info/RECORD
