Metadata-Version: 2.1
Name: wafflehacks-mailer
Version: 0.2.2
Summary: The Python SDK for the WaffleHacks mailer
Author: Alex Krantz
Author-email: alex@krantz.dev
Requires-Python: >=3.8,<4.0
Classifier: Programming Language :: Python :: 3
Classifier: Programming Language :: Python :: 3.8
Classifier: Programming Language :: Python :: 3.9
Classifier: Programming Language :: Python :: 3.10
Classifier: Programming Language :: Python :: 3.11
Requires-Dist: aiohttp[speedups] (>=3.8.4,<4.0.0)
Requires-Dist: requests (>=2.28.2,<3.0.0)
